COPYING
COPYING.LESSER
MANIFEST.in
README.ipynb
README.md
README.rst
VERSION
requirements.txt
setup.cfg
setup.py
tox.ini
zetup.ini
modeled.netconf.egg-info/PKG-INFO
modeled.netconf.egg-info/SOURCES.txt
modeled.netconf.egg-info/dependency_links.txt
modeled.netconf.egg-info/requires.txt
modeled.netconf.egg-info/top_level.txt
modeled/netconf/__init__.py
modeled/netconf/zetup_config.py
modeled/netconf/yang/__init__.py
modeled/netconf/yang/common.py
modeled/netconf/yang/container.py
modeled/netconf/yang/module.py
modeled/netconf/yang/rpc.py
test/conftest.py
test/test_yang.py
test/turing-machine.yang
test/turing_machine-program.yaml
test/turing_machine.py