Metadata-Version: 1.1
Name: modeled.netconf
Version: 0.0.1
Summary: Highly Pythonized NETCONF and YANG
Home-page: https://bitbucket.org/userzimmermann/python-modeled.netconf
Author: Stefan Zimmermann
Author-email: zimmermann.code@gmail.com
License: LGPLv3
Keywords: netconf,yang,yin,server,client,ssh,rpc,xml,xmlrpc,modeled,model,modeling,modelled,modelling,serialization,exchange,mapping,pyang,paramiko,python3
Platform: UNKNOWN
Classifier: Development Status :: 3 - Alpha
Classifier: Intended Audience :: Developers
Classifier: License :: OSI Approved :: GNU Library or Lesser General Public License (LGPL)
Classifier: Operating System :: OS Independent
Classifier: Topic :: Software Development
Classifier: Topic :: Utilities
Classifier: Programming Language :: Python
Classifier: Programming Language :: Python :: 2.7
Classifier: Programming Language :: Python :: 3.3
Classifier: Programming Language :: Python :: 3.4
